README.md
setup.py
MathDownCompat.egg-info/PKG-INFO
MathDownCompat.egg-info/SOURCES.txt
MathDownCompat.egg-info/dependency_links.txt
MathDownCompat.egg-info/entry_points.txt
MathDownCompat.egg-info/not-zip-safe
MathDownCompat.egg-info/requires.txt
MathDownCompat.egg-info/top_level.txt
mathdowncompat/main.py
mathdowncompat/converters/__init__.py
mathdowncompat/converters/image.py
mathdowncompat/converters/mathml.py