Metadata-Version: 1.1
Name: MathDownCompat
Version: 0.0.1
Summary: MathTex compatibility for in-browser markdown using MathJax, MathML, and/or images
Home-page: https://github.com/alvinwan/mathdowncompat
Author: Alvin Wan
Author-email: hi@alvinwan.com
License: Apache
Download-URL: https://github.com/alvinwan/mathdowncompat/archive/0.0.1.zip
Platform: UNKNOWN
Classifier: Topic :: Utilities
Classifier: Intended Audience :: Developers
Classifier: Programming Language :: Python :: 3
Classifier: Topic :: Software Development :: Libraries
